{"count":3494,"photos":[{"upload_date":"21 January 2007","owner_name":"Busa P\u00e9ter","photo_id":522084,"longitude":17.470493000000001,"height":350,"width":500,"photo_title":"In Memoriam Antoine de Saint-Exup\u00e9ry","latitude":47.867077000000002,"owner_url":"http://www.panoramio.com/user/109117","photo_url":"http://www.panoramio.com/photo/522084","photo_file_url":"http://mw2.google.com/mw-panoramio/photos/medium/522084.jpg","owner_id":109117},{"upload_date":"12 March 2007","owner_name":"@mabut","photo_id":1289207,"longitude":-4.0199660000000002,"height":337,"width":500,"photo_title":"Silouette","latitude":31.187546000000001,"owner_url":"http://www.panoramio.com/user/232099","photo_url":"http://www.panoramio.com/photo/1289207","photo_file_url":"http://mw2.google.com/mw-panoramio/photos/medium/1289207.jpg","owner_id":232099},{"upload_date":"12 March 2007","owner_name":"Jean-Michel Raggioli","photo_id":1282387,"longitude":-61.017049999999998,"height":400,"width":500,"photo_title":"Thunderstorm in Martinique","latitude":14.500819,"owner_url":"http://www.panoramio.com/user/49870","photo_url":"http://www.panoramio.com/photo/1282387","photo_file_url":"http://mw2.google.com/mw-panoramio/photos/medium/1282387.jpg","owner_id":49870},{"upload_date":"20 January 2011","owner_name":"Dominik M. Ram\u00edk","photo_id":46817885,"longitude":-178.13709299999999,"height":330,"width":500,"photo_title":"Dusk in Tufulega, Futuna Island","latitude":-14.310613,"owner_url":"http://www.panoramio.com/user/919358","photo_url":"http://www.panoramio.com/photo/46817885","photo_file_url":"http://mw2.google.com/mw-panoramio/photos/medium/46817885.jpg","owner_id":919358},{"upload_date":"02 May 2011","owner_name":"Klarens","photo_id":52034419,"longitude":-6.3821979999999998,"height":500,"width":500,"photo_title":"The Dark Hedges","latitude":55.135249000000002,"owner_url":"http://www.panoramio.com/user/5851975","photo_url":"http://www.panoramio.com/photo/52034419","photo_file_url":"http://mw2.google.com/mw-panoramio/photos/medium/52034419.jpg","owner_id":5851975},{"upload_date":"25 June 2006","owner_name":"Miguel Coranti","photo_id":27932,"longitude":-64.404944999999998,"height":375,"width":500,"photo_title":"Atardecer en Embalse","latitude":-32.202924000000003,"owner_url":"http://www.panoramio.com/user/4483","photo_url":"http://www.panoramio.com/photo/27932","photo_file_url":"http://mw2.google.com/mw-panoramio/photos/medium/27932.jpg","owner_id":4483},{"upload_date":"18 January 2011","owner_name":"Michael  \u5b89\u8def","photo_id":46752123,"longitude":120.52718600000003,"height":370,"width":500,"photo_title":" Beautiful Taiwan----Rising ","latitude":23.327833999999999,"owner_url":"http://www.panoramio.com/user/2780232","photo_url":"http://www.panoramio.com/photo/46752123","photo_file_url":"http://mw2.google.com/mw-panoramio/photos/medium/46752123.jpg","owner_id":2780232},{"upload_date":"17 June 2006","owner_name":"Roberto Garcia","photo_id":25514,"longitude":-84.693431854248004,"height":375,"width":500,"photo_title":"Arenal","latitude":10.479372089916,"owner_url":"http://www.panoramio.com/user/4112","photo_url":"http://www.panoramio.com/photo/25514","photo_file_url":"http://mw2.google.com/mw-panoramio/photos/medium/25514.jpg","owner_id":4112},{"upload_date":"02 February 2006","owner_name":"heavenearth","photo_id":9439,"longitude":-151.75,"height":375,"width":500,"photo_title":"Bora Bora","latitude":-16.5,"owner_url":"http://www.panoramio.com/user/1600","photo_url":"http://www.panoramio.com/photo/9439","photo_file_url":"http://mw2.google.com/mw-panoramio/photos/medium/9439.jpg","owner_id":1600},{"upload_date":"04 July 2011","owner_name":"Mahdi Kalhor","photo_id":55228074,"place_id":"72e961480bdb78ea84504b38a20eed35385b7ab3","longitude":57.773236999999995,"height":375,"width":500,"photo_title":"\u06a9\u0644\u0648\u062a \u0628\u0632\u0631\u06af\u062a\u0631\u06cc\u0646 \u0634\u0647\u0631 \u06a9\u0644\u0648\u062e\u06cc \u062f\u0646\u06cc\u0627 \u062f\u0631 \u0628\u06cc\u0627\u0628\u0627\u0646 \u0644\u0648\u062a\u060c \u06351 'Kalut' in Lut Desert, To all European Panoramio members. Info 1st comment  ","latitude":30.792722999999999,"owner_url":"http://www.panoramio.com/user/1171864","photo_url":"http://www.panoramio.com/photo/55228074","photo_file_url":"http://mw2.google.com/mw-panoramio/photos/medium/55228074.jpg","owner_id":1171864},{"upload_date":"25 November 2007","owner_name":"Mark Simms","photo_id":6126294,"longitude":-0.27519464492798001,"height":500,"width":489,"photo_title":"Richmond Deer","latitude":51.445889875669998,"owner_url":"http://www.panoramio.com/user/1130880","photo_url":"http://www.panoramio.com/photo/6126294","photo_file_url":"http://mw2.google.com/mw-panoramio/photos/medium/6126294.jpg","owner_id":1130880},{"upload_date":"09 December 2006","owner_name":"Cyrill","photo_id":97671,"longitude":30.78603,"height":375,"width":500,"photo_title":"kin-dza-dza","latitude":46.638703999999997,"owner_url":"http://www.panoramio.com/user/13058","photo_url":"http://www.panoramio.com/photo/97671","photo_file_url":"http://mw2.google.com/mw-panoramio/photos/medium/97671.jpg","owner_id":13058},{"upload_date":"25 May 2008","owner_name":"VFedele","photo_id":10574161,"longitude":148.682098,"height":346,"width":500,"photo_title":"SILHOUETTE","latitude":-35.299996,"owner_url":"http://www.panoramio.com/user/766550","photo_url":"http://www.panoramio.com/photo/10574161","photo_file_url":"http://mw2.google.com/mw-panoramio/photos/medium/10574161.jpg","owner_id":766550},{"upload_date":"05 October 2006","owner_name":"Norbert MAIER","photo_id":57823,"longitude":12.900009155273001,"height":333,"width":500,"photo_title":"Maria Alm","latitude":47.409967629268003,"owner_url":"http://www.panoramio.com/user/8060","photo_url":"http://www.panoramio.com/photo/57823","photo_file_url":"http://mw2.google.com/mw-panoramio/photos/medium/57823.jpg","owner_id":8060},{"upload_date":"24 February 2011","owner_name":"Fabio Roman","photo_id":48619132,"longitude":12.346475999999999,"height":500,"width":500,"photo_title":"Laghi Revine dal monte Pizzoc ","latitude":46.038831999999999,"owner_url":"http://www.panoramio.com/user/646873","photo_url":"http://www.panoramio.com/photo/48619132","photo_file_url":"http://mw2.google.com/mw-panoramio/photos/medium/48619132.jpg","owner_id":646873},{"upload_date":"01 April 2007","owner_name":"rosina lamberti","photo_id":1578881,"longitude":145.14175399999999,"height":474,"width":500,"photo_title":"Rosina Lamberti,Sunset,Templestowe , Victoria, Australia","latitude":-37.766371999999997,"owner_url":"http://www.panoramio.com/user/140796","photo_url":"http://www.panoramio.com/photo/1578881","photo_file_url":"http://mw2.google.com/mw-panoramio/photos/medium/1578881.jpg","owner_id":140796},{"upload_date":"24 September 2010","owner_name":"OLYMPIST \u00a9","photo_id":41234541,"longitude":27.37653499999999,"height":373,"width":500,"photo_title":"G\u00f6lt\u00fcrkb\u00fck\u00fc / Bodrum...  * Olympist \u00a9 * ","latitude":37.132249000000002,"owner_url":"http://www.panoramio.com/user/3908287","photo_url":"http://www.panoramio.com/photo/41234541","photo_file_url":"http://mw2.google.com/mw-panoramio/photos/medium/41234541.jpg","owner_id":3908287},{"upload_date":"21 December 2006","owner_name":"mikel ortega","photo_id":204924,"longitude":-1.806951,"height":346,"width":500,"photo_title":"zaldiak","latitude":43.245139999999999,"owner_url":"http://www.panoramio.com/user/2575","photo_url":"http://www.panoramio.com/photo/204924","photo_file_url":"http://mw2.google.com/mw-panoramio/photos/medium/204924.jpg","owner_id":2575},{"upload_date":"25 December 2006","owner_name":"Andrzej Wierzcho\u0144","photo_id":233619,"longitude":21.035727999999999,"height":500,"width":500,"photo_title":"Warsaw Bridge 01 [www.wierzchon.com]","latitude":52.242353000000001,"owner_url":"http://www.panoramio.com/user/47836","photo_url":"http://www.panoramio.com/photo/233619","photo_file_url":"http://mw2.google.com/mw-panoramio/photos/medium/233619.jpg","owner_id":47836},{"upload_date":"18 December 2010","owner_name":"ZEUS74","photo_id":45214668,"place_id":"87c1216871b2fbb70e1519f7ff28890c1843902b","longitude":-0.6199980000000096,"height":335,"width":500,"photo_title":"MIENTRAS QUEDE UN REFLEJO HABRA UNA FOTO \u003c 1st Prize  Scenery December 2010 \u003e","latitude":38.178075999999997,"owner_url":"http://www.panoramio.com/user/3100440","photo_url":"http://www.panoramio.com/photo/45214668","photo_file_url":"http://mw2.google.com/mw-panoramio/photos/medium/45214668.jpg","owner_id":3100440}],"has_more":true,"map_location":{"lat":8.6844385000000024,"lon":4.139187442791064,"panoramio_zoom":17}}